{"version": "0", "root": "", "base": {"schema": "/schema", "schema.version": "/schema/version", "config": "/config", "config.maintenance": "/config/maintenance", "config.primary_node": "/config/primary_node", "config.upstream_ip": "/config/upstream_ip", "config.migration_target_selector": "/config/migration_target_selector", "lock": "/locks", "lock.primary_node": "/locks/primary_node", "lock.flush_lock": "/locks/flush_lock", "lock.domain_migrate": "/locks/domain_migrate", "cmd": "/cmd", "cmd.nodes": "/cmd/nodes", "cmd.domains": "/cmd/domains", "cmd.ceph": "/cmd/ceph", "node": "/nodes", "domain": "/domains", "network": "/networks", "storage": "/ceph", "storage.util": "/ceph/util", "osd": "/ceph/osds", "pool": "/ceph/pools", "volume": "/ceph/volumes", "snapshot": "/ceph/snapshots"}, "node": {"keepalive": "/keepalive", "mode": "/daemonmode", "data.active_schema": "/activeschema", "data.latest_schema": "/latestschema", "data.static": "/staticdata", "counts.provisioned_domains": "/domainscount", "counts.running_domains": "/runningdomains", "counts.networks": "/networkscount", "state.daemon": "/daemonstate", "state.router": "/routerstate", "state.domain": "/domainstate", "vcpu.allocated": "/vcpualloc", "memory.total": "/memtotal", "memory.used": "/memused", "memory.free": "/memfree", "memory.allocated": "/memalloc", "memory.provisioned": "/memprov", "ipmi.hostname": "/ipmihostname", "ipmi.username": "/ipmiusername", "ipmi.password": "/ipmipassword"}, "domain": {"name": "", "xml": "/xml", "state": "/state", "profile": "/profile", "stats": "/stats", "node": "/node", "last_node": "/lastnode", "failed_reason": "/failedreason", "console.log": "/consolelog", "console.vnc": "/vnc", "meta.autostart": "/node_autostart", "meta.migrate_method": "/migration_method", "meta.node_selector": "/node_selector", "meta.node_limit": "/node_limit"}, "network": {"type": "/nettype", "rules": "/firewall_rules", "nameservers": "/name_servers", "domain": "/domain", "ip4.gateway": "/ip4_gateway", "ip4.network": "/ip4_network", "ip4.dhcp": "/dhcp4_flag", "ip4.reservations": "/dhcp4_reservations", "ip4.dhcp_start": "/dhcp4_start", "ip4.dhcp_end": "/dhcp4_end", "ip6.gateway": "/ip6_gateway", "ip6.network": "/ip6_network", "ip6.dhcp": "/dhcp6_flag"}, "osd": {"node": "/node", "device": "/device", "stats": "/stats"}, "pool": {"pgs": "/pgs", "stats": "/stats"}, "volume": {"stats": "/stats"}, "snapshot": {"stats": "/stats"}}